pycommon/__init__.py
pycommon/auth/__init__.py
pycommon/auth/jwt/__init__.py
pycommon/auth/jwt/jwt_bearer.py
pycommon/auth/jwt/tests/__init__.py
pycommon/auth/jwt/tests/test_jwt_bearer.py
pycommon/db/__init__.py
pycommon/db/utils.py
pycommon/db/tests/__init__.py
pycommon/db/tests/test_base.py
pycommon/db/tests/test_session_manager.py
pycommon/utils/__init__.py
pycommon/utils/result.py
pycommon/utils/tests/__init__.py
pycommon/utils/tests/test_result.py
pycommon_kit-0.0.9.dist-info/METADATA
pycommon_kit-0.0.9.dist-info/WHEEL
pycommon_kit-0.0.9.dist-info/top_level.txt
pycommon_kit-0.0.9.dist-info/RECORD
